hdate-1.1.2.dist-info/METADATA
hdate-1.1.2.dist-info/WHEEL
hdate-1.1.2.dist-info/entry_points.txt
hdate-1.1.2.dist-info/licenses/LICENSE
hdate/__init__.py
hdate/converters.py
hdate/daf_yomi.py
hdate/date_info.py
hdate/gematria.py
hdate/hebrew_date.py
hdate/holidays.py
hdate/location.py
hdate/omer.py
hdate/parasha.py
hdate/py.typed
hdate/tekufot.py
hdate/translations.py
hdate/translations/en.json
hdate/translations/fr.json
hdate/translations/he.json
hdate/translator.py
hdate/zmanim.py
hdate-1.1.2.dist-info/RECORD
