Metadata-Version: 2.1
Name: hdate
Version: 1.1.2
Summary: Jewish/Hebrew date and Zmanim in native Python 2.7/3.x
Author-Email: Royi Reshef <roy.myapp@gmail.com>
Maintainer-Email: Tsvi Mostovicz <ttmost@gmail.com>
License: GPL-3.0-or-later
Classifier: Development Status :: 5 - Production/Stable
Classifier: Topic :: Software Development :: Libraries
Project-URL: repository, https://github.com/py-libhdate/py-libhdate
Project-URL: documentation, https://py-libhdate.readthedocs.io/en/latest/
Requires-Python: >=3.9
Requires-Dist: num2words>=0.5.14
Provides-Extra: astral
Requires-Dist: astral>=2.2; extra == "astral"
